CHANGES
LICENSE
MANIFEST.in
README.rst
setup.py
ibm_db_alembic/__init__.py
ibm_db_alembic/ibm_db.py
ibm_db_alembic.egg-info/PKG-INFO
ibm_db_alembic.egg-info/SOURCES.txt
ibm_db_alembic.egg-info/dependency_links.txt
ibm_db_alembic.egg-info/not-zip-safe
ibm_db_alembic.egg-info/requires.txt
ibm_db_alembic.egg-info/top_level.txt