Metadata-Version: 1.1
Name: ibm-db-alembic
Version: 0.2.0
Summary: Alembic support for IBM Data Servers
Home-page: http://pypi.python.org/pypi/ibm_db_alembic/
Author: IBM Application Development Team
Author-email: opendev@us.ibm.com
License: Apache License 2.0
Keywords: Alembic database interface IBM Data Servers DB2
Platform: All
Classifier: Development Status :: 4 - Beta
Classifier: Intended Audience :: Developers
Classifier: License :: OSI Approved :: Apache Software License
Classifier: Operating System :: OS Independent
Classifier: Topic :: Database :: Front-Ends
